verto/Verto.py
verto/VertoExtension.py
verto/__init__.py
verto/processor-info.json
verto/errors/ArgumentDefinitionError.py
verto/errors/ArgumentMissingError.py
verto/errors/ArgumentValueError.py
verto/errors/BlockquoteMissingFooterError.py
verto/errors/CustomArgumentRulesError.py
verto/errors/Error.py
verto/errors/HtmlParseError.py
verto/errors/ImageCaptionContainsImageError.py
verto/errors/ImageMissingCaptionError.py
verto/errors/InteractiveMissingTextError.py
verto/errors/InteractiveTextContainsInteractiveError.py
verto/errors/NoSourceLinkError.py
verto/errors/NoVideoIdentifierError.py
verto/errors/PanelMissingSubtitleError.py
verto/errors/PanelMissingTitleError.py
verto/errors/StyleError.py
verto/errors/TagNotMatchedError.py
verto/errors/UnsupportedVideoPlayerError.py
verto/errors/__init__.py
verto/html-templates/blockquote.html
verto/html-templates/boxed-text.html
verto/html-templates/button-link.html
verto/html-templates/conditional.html
verto/html-templates/external-link.html
verto/html-templates/glossary-link.html
verto/html-templates/heading.html
verto/html-templates/iframe.html
verto/html-templates/image-inline.html
verto/html-templates/image.html
verto/html-templates/interactive.html
verto/html-templates/panel.html
verto/html-templates/relative-file-link.html
verto/html-templates/relative-link.html
verto/html-templates/scratch-inline.html
verto/html-templates/scratch.html
verto/html-templates/table-of-contents.html
verto/html-templates/video-vimeo.html
verto/html-templates/video-youtube.html
verto/html-templates/video.html
verto/images/verto-logo.png
verto/processors/BlockquoteBlockProcessor.py
verto/processors/CommentPreprocessor.py
verto/processors/ConditionalProcessor.py
verto/processors/ExternalLinkPattern.py
verto/processors/GenericContainerBlockProcessor.py
verto/processors/GenericTagBlockProcessor.py
verto/processors/GlossaryLinkPattern.py
verto/processors/HeadingBlockProcessor.py
verto/processors/ImageContainerBlockProcessor.py
verto-1.1.1.dist-info/METADATA
verto-1.1.1.dist-info/WHEEL
verto-1.1.1.dist-info/top_level.txt
verto-1.1.1.dist-info/RECORD
