Metadata-Version: 2.1
Name: verto
Version: 1.1.1
Summary: Verto is an extension of the Python Markdown package, which allows authors to include complex HTML elements with simple text tags in their Markdown.
Author: University of Canterbury Computer Science Education Research Group
Author-email: csse-education-research@canterbury.ac.nz
License: MIT
Project-URL: Issue Tracker, https://github.com/uccser/verto/issues
Project-URL: Documentation, https://verto.readthedocs.io/en/latest/
Project-URL: Changelog, http://verto.readthedocs.io/en/latest/changelog.html
Project-URL: Source Code, https://github.com/uccser/verto
Keywords: markdown,verto,development,textbook,converter,media,richtext,interactive,education,html,book,author,extension
Classifier: Intended Audience :: Developers
Classifier: Intended Audience :: Education
Classifier: License :: OSI Approved :: MIT License
Classifier: Operating System :: MacOS :: MacOS X
Classifier: Operating System :: Microsoft :: Windows
Classifier: Operating System :: POSIX
Classifier: Programming Language :: Python :: 3
Classifier: Topic :: Text Processing :: Markup
Classifier: Topic :: Text Processing :: Markup :: HTML
Requires-Python: >=3.8
Requires-Dist: markdown (==2.6.11)
Requires-Dist: Jinja2 (==3.0.1)
Requires-Dist: python-slugify (==5.0.2)
